{
  "appointments": [
    {
      "id": 1,
      "title": "Visitar la casa de Gordon Freeman",
      "shortDescription": "Ir a ciudad 17 a hacer un relevamiento de la casa de Gordon Freeman",
      "dateAppointment": "11/19/2021",
      "hour": " 4:05:00 AM",
      "agent": "Gordon Freeman",
      "propertie": "34634",
      "stateAppointment": "En Proceso",
      "cellphone": "8736284",
      "email": "facundoInfled@gmail.com",
      "fullName": "Facundo Infeld"
    },
    {
      "id": 2,
      "title": "oiuweruyw",
      "shortDescription": "lkjsdhlfkj987",
      "dateAppointment": "11/19/2021",
      "hour": " 2:08:00 AM",
      "agent": "Gordon Freeman",
      "propertie": "235",
      "stateAppointment": "En Proceso",
      "cellphone": 23423423,
      "email": "juanespinoza@gmail.com",
      "fullName": "sadkjfhlsakdjfhls"
    }
  ]
}